typhoon/__init__.py
typhoon/__init__.pyi
typhoon/helper.py
typhoon/helper.pyi
typhoon/py.typed
typhoon/typhoon.cpython-314-s390x-linux-gnu.so
typhoon/typhoon.pyi
typhoon/woehler.py
typhoon/woehler.pyi
typhoon_rainflow-0.2.1.dist-info/METADATA
typhoon_rainflow-0.2.1.dist-info/WHEEL
typhoon_rainflow-0.2.1.dist-info/RECORD
