Metadata-Version: 2.4
Name: typhoon-rainflow
Version: 0.2.1
Classifier: Programming Language :: Rust
Classifier: Programming Language :: Python :: Implementation :: CPython
Classifier: Programming Language :: Python :: Implementation :: PyPy
Classifier: Typing :: Typed
Requires-Dist: numpy
Requires-Dist: pandas
Requires-Dist: nox ; extra == 'test'
Provides-Extra: test
Summary: Fast rainflow counting for streaming input written in Rust
Author: Markus Wegmann
Author-email: mw@technokrat.ch
Requires-Python: >=3.8
